gcgman/__init__.py
gcgman-1.4.data/scripts/gcgman
gcgman-1.4.dist-info/LICENSE
gcgman-1.4.dist-info/METADATA
gcgman-1.4.dist-info/WHEEL
gcgman-1.4.dist-info/top_level.txt
gcgman-1.4.dist-info/RECORD
